pytplot/__init__.py
pytplot/del_data.py
pytplot/get_data.py
pytplot/get_timespan.py
pytplot/get_ylimits.py
pytplot/link.py
pytplot/options.py
pytplot/replace_data.py
pytplot/spedas_colorbar.py
pytplot/store_data.py
pytplot/timebar.py
pytplot/timespan.py
pytplot/timestamp.py
pytplot/tlimit.py
pytplot/tplot.py
pytplot/tplot_copy.py
pytplot/tplot_names.py
pytplot/tplot_options.py
pytplot/tplot_rename.py
pytplot/tplot_utilities.py
pytplot/version.txt
pytplot/xlim.py
pytplot/ylim.py
pytplot/zlim.py
pytplot/AncillaryPlots/__init__.py
pytplot/AncillaryPlots/position_mars_2d.py
pytplot/AncillaryPlots/position_mars_3d.py
pytplot/AncillaryPlots/spec_slicer.py
pytplot/HTMLPlotter/TVarFigure1D.py
pytplot/HTMLPlotter/TVarFigureAlt.py
pytplot/HTMLPlotter/TVarFigureMap.py
pytplot/HTMLPlotter/TVarFigureSpec.py
pytplot/HTMLPlotter/__init__.py
pytplot/HTMLPlotter/generate.py
pytplot/HTMLPlotter/CustomModels/__init__.py
pytplot/HTMLPlotter/CustomModels/colorbarsidetitle.py
pytplot/HTMLPlotter/CustomModels/timestamp.py
pytplot/QtPlotter/PyTPlot_Exporter.py
pytplot/QtPlotter/TVarFigure1D.py
pytplot/QtPlotter/TVarFigureAlt.py
pytplot/QtPlotter/TVarFigureAxisOnly.py
pytplot/QtPlotter/TVarFigureMap.py
pytplot/QtPlotter/TVarFigureSpec.py
pytplot/QtPlotter/__init__.py
pytplot/QtPlotter/generate.py
pytplot/QtPlotter/CustomAxis/AxisItem.py
pytplot/QtPlotter/CustomAxis/BlankAxis.py
pytplot/QtPlotter/CustomAxis/DateAxis.py
pytplot/QtPlotter/CustomAxis/NonLinearAxis.py
pytplot/QtPlotter/CustomAxis/__init__.py
pytplot/QtPlotter/CustomImage/ColorbarImage.py
pytplot/QtPlotter/CustomImage/UpdatingImage.py
pytplot/QtPlotter/CustomImage/__init__.py
pytplot/QtPlotter/CustomLegend/CustomLegend.py
pytplot/QtPlotter/CustomLegend/__init__.py
pytplot/QtPlotter/CustomLinearRegionItem/CustomLinearRegionItem.py
pytplot/QtPlotter/CustomViewBox/CustomVB.py
pytplot/QtPlotter/CustomViewBox/NoPaddingPlot.py
pytplot/QtPlotter/CustomViewBox/__init__.py
pytplot/exporters/__init__.py
pytplot/exporters/tplot_ascii.py
pytplot-1.7.28.dist-info/LICENSE
pytplot-1.7.28.dist-info/METADATA
pytplot-1.7.28.dist-info/WHEEL
pytplot-1.7.28.dist-info/top_level.txt
pytplot-1.7.28.dist-info/RECORD
