Metadata-Version: 2.1
Name: pytplot
Version: 1.7.28
Summary: A python version of IDL tplot libraries
Home-page: https://github.com/MAVENSDC/pytplot
Author: MAVEN SDC
Author-email: mavensdc@lasp.colorado.edu
Keywords: tplot,maven,lasp,IDL,spedas
Classifier: Development Status :: 5 - Production/Stable
Classifier: Environment :: Console
Classifier: Intended Audience :: Science/Research
Classifier: Operating System :: OS Independent
Classifier: Programming Language :: Python :: 3.7
Classifier: Topic :: Utilities
Requires-Python: >=3.6
License-File: LICENSE
Requires-Dist: numpy (>=1.20.0)
Requires-Dist: bokeh (>=1.1)
Requires-Dist: pyqtgraph (>=0.11.1)
Requires-Dist: pandas
Requires-Dist: matplotlib
Requires-Dist: scipy
Requires-Dist: cdflib
Requires-Dist: xarray
Requires-Dist: pyqt5 (>=5.15.2)
Requires-Dist: pyqtwebengine (>=5.15.2)
Provides-Extra: tests
Requires-Dist: pytest ; extra == 'tests'
Requires-Dist: pytest-cov ; extra == 'tests'
Requires-Dist: coveralls ; extra == 'tests'
Requires-Dist: flake8 ; extra == 'tests'
Requires-Dist: mypy ; extra == 'tests'
Requires-Dist: astropy ; extra == 'tests'
